README.md
dendrogram_purity.py
setup.py
ete_dendrogram_purity.egg-info/PKG-INFO
ete_dendrogram_purity.egg-info/SOURCES.txt
ete_dendrogram_purity.egg-info/dependency_links.txt
ete_dendrogram_purity.egg-info/requires.txt
ete_dendrogram_purity.egg-info/top_level.txt